edgegap_service/__init__.py
edgegap_service/_configuration.py
edgegap_service/_documentation.py
edgegap_service/_environment.py
edgegap_service/_scheduling.py
edgegap_service/_service.py
edgegap_service/_templating.py
edgegap_service/health/__init__.py
edgegap_service/health/_health.py
edgegap_service/health/_model.py
edgegap_service/health/checks/__init__.py
edgegap_service/health/checks/_consul.py
edgegap_service/health/checks/_database.py
edgegap_service/health/checks/_interface.py
edgegap_service/health/checks/_model.py
edgegap_service/logging/__init__.py
edgegap_service/logging/_configuration.py
edgegap_service/logging/_logger.py
edgegap_service/static/html/index.html
edgegap_service/static/images/favicon.ico
edgegap_service-1.10.12.dist-info/LICENSE
edgegap_service-1.10.12.dist-info/METADATA
edgegap_service-1.10.12.dist-info/WHEEL
edgegap_service-1.10.12.dist-info/RECORD
