Metadata-Version: 2.1
Name: edgegap-service
Version: 1.10.12
Summary: The Edgegap Service library includes various tools and helpers for creating FastAPI Service with easy integration. It is designed for use within the Edgegap organization.
Author: Bastien Roy
Author-email: bastien@edgegap.com
Requires-Python: >=3.10,<4.0
Classifier: Programming Language :: Python :: 3
Classifier: Programming Language :: Python :: 3.10
Classifier: Programming Language :: Python :: 3.11
Classifier: Programming Language :: Python :: 3.12
Requires-Dist: colorama (>=0.4.6,<0.5.0)
Requires-Dist: edgegap-consul (>=1.0.0,<2.0.0)
Requires-Dist: edgegap-database (>=1.0.0,<2.0.0)
Requires-Dist: edgegap-logging (>=1.0.0,<2.0.0)
Requires-Dist: edgegap-scheduling (>=1.0.0,<2.0.0)
Requires-Dist: edgegap-settings (>=1.0.0,<2.0.0)
Requires-Dist: elastic-apm (>=6.22.0,<7.0.0)
Requires-Dist: fastapi (>=0.115.2,<0.116.0)
Requires-Dist: jinja2 (>=3.1.3,<4.0.0)
Requires-Dist: pydantic (>=2.7.1,<3.0.0)
Requires-Dist: pydantic-settings (>=2.2.1,<3.0.0)
Requires-Dist: python-logstash-async (>=3.0.0,<4.0.0)
